{
  "model_version": "elo-v1+squad30+form",
  "elo_version": "elo-v1",
  "elo_weight": 0.7,
  "generated_at": "2026-05-09T00:55:25Z",
  "bracket_format": "fifa-2026",
  "flags": {
    "Algeria": "dz",
    "Argentina": "ar",
    "Australia": "au",
    "Austria": "at",
    "Belgium": "be",
    "Bosnia and Herzegovina": "ba",
    "Brazil": "br",
    "Canada": "ca",
    "Cape Verde": "cv",
    "Colombia": "co",
    "Croatia": "hr",
    "Cura\u00e7ao": "cw",
    "Czech Republic": "cz",
    "DR Congo": "cd",
    "Ecuador": "ec",
    "Egypt": "eg",
    "England": "gb-eng",
    "France": "fr",
    "Germany": "de",
    "Ghana": "gh",
    "Haiti": "ht",
    "Iran": "ir",
    "Iraq": "iq",
    "Ivory Coast": "ci",
    "Japan": "jp",
    "Jordan": "jo",
    "Mexico": "mx",
    "Morocco": "ma",
    "Netherlands": "nl",
    "New Zealand": "nz",
    "Norway": "no",
    "Panama": "pa",
    "Paraguay": "py",
    "Portugal": "pt",
    "Qatar": "qa",
    "Saudi Arabia": "sa",
    "Scotland": "gb-sct",
    "Senegal": "sn",
    "South Africa": "za",
    "South Korea": "kr",
    "Spain": "es",
    "Sweden": "se",
    "Switzerland": "ch",
    "Tunisia": "tn",
    "Turkey": "tr",
    "United States": "us",
    "Uruguay": "uy",
    "Uzbekistan": "uz"
  },
  "groups": [
    {
      "name": "A",
      "standings": [
        {
          "team": "Mexico",
          "rating": 1792,
          "predicted_points": 9,
          "position": 1,
          "qualifies_as": "winner"
        },
        {
          "team": "South Korea",
          "rating": 1774,
          "predicted_points": 6,
          "position": 2,
          "qualifies_as": "runner_up"
        },
        {
          "team": "Czech Republic",
          "rating": 1671,
          "predicted_points": 3,
          "position": 3,
          "qualifies_as": "eliminated"
        },
        {
          "team": "South Africa",
          "rating": 1623,
          "predicted_points": 0,
          "position": 4,
          "qualifies_as": "eliminated"
        }
      ]
    },
    {
      "name": "B",
      "standings": [
        {
          "team": "Switzerland",
          "rating": 1882,
          "predicted_points": 9,
          "position": 1,
          "qualifies_as": "winner"
        },
        {
          "team": "Canada",
          "rating": 1797,
          "predicted_points": 6,
          "position": 2,
          "qualifies_as": "runner_up"
        },
        {
          "team": "Bosnia and Herzegovina",
          "rating": 1694,
          "predicted_points": 3,
          "position": 3,
          "qualifies_as": "eliminated"
        },
        {
          "team": "Qatar",
          "rating": 1552,
          "predicted_points": 0,
          "position": 4,
          "qualifies_as": "eliminated"
        }
      ]
    },
    {
      "name": "C",
      "standings": [
        {
          "team": "Brazil",
          "rating": 1937,
          "predicted_points": 9,
          "position": 1,
          "qualifies_as": "winner"
        },
        {
          "team": "Morocco",
          "rating": 1864,
          "predicted_points": 6,
          "position": 2,
          "qualifies_as": "runner_up"
        },
        {
          "team": "Scotland",
          "rating": 1734,
          "predicted_points": 3,
          "position": 3,
          "qualifies_as": "best_third"
        },
        {
          "team": "Haiti",
          "rating": 1650,
          "predicted_points": 0,
          "position": 4,
          "qualifies_as": "eliminated"
        }
      ]
    },
    {
      "name": "D",
      "standings": [
        {
          "team": "Turkey",
          "rating": 1878,
          "predicted_points": 9,
          "position": 1,
          "qualifies_as": "winner"
        },
        {
          "team": "Paraguay",
          "rating": 1829,
          "predicted_points": 6,
          "position": 2,
          "qualifies_as": "runner_up"
        },
        {
          "team": "United States",
          "rating": 1771,
          "predicted_points": 3,
          "position": 3,
          "qualifies_as": "best_third"
        },
        {
          "team": "Australia",
          "rating": 1792,
          "predicted_points": 0,
          "position": 4,
          "qualifies_as": "eliminated"
        }
      ]
    },
    {
      "name": "E",
      "standings": [
        {
          "team": "Ecuador",
          "rating": 1906,
          "predicted_points": 9,
          "position": 1,
          "qualifies_as": "winner"
        },
        {
          "team": "Germany",
          "rating": 1877,
          "predicted_points": 6,
          "position": 2,
          "qualifies_as": "runner_up"
        },
        {
          "team": "Ivory Coast",
          "rating": 1825,
          "predicted_points": 3,
          "position": 3,
          "qualifies_as": "best_third"
        },
        {
          "team": "Cura\u00e7ao",
          "rating": 1631,
          "predicted_points": 0,
          "position": 4,
          "qualifies_as": "eliminated"
        }
      ]
    },
    {
      "name": "F",
      "standings": [
        {
          "team": "Japan",
          "rating": 1903,
          "predicted_points": 9,
          "position": 1,
          "qualifies_as": "winner"
        },
        {
          "team": "Netherlands",
          "rating": 1891,
          "predicted_points": 6,
          "position": 2,
          "qualifies_as": "runner_up"
        },
        {
          "team": "Sweden",
          "rating": 1741,
          "predicted_points": 3,
          "position": 3,
          "qualifies_as": "best_third"
        },
        {
          "team": "Tunisia",
          "rating": 1710,
          "predicted_points": 0,
          "position": 4,
          "qualifies_as": "eliminated"
        }
      ]
    },
    {
      "name": "G",
      "standings": [
        {
          "team": "Belgium",
          "rating": 1870,
          "predicted_points": 9,
          "position": 1,
          "qualifies_as": "winner"
        },
        {
          "team": "Iran",
          "rating": 1738,
          "predicted_points": 6,
          "position": 2,
          "qualifies_as": "runner_up"
        },
        {
          "team": "Egypt",
          "rating": 1738,
          "predicted_points": 3,
          "position": 3,
          "qualifies_as": "best_third"
        },
        {
          "team": "New Zealand",
          "rating": 1642,
          "predicted_points": 0,
          "position": 4,
          "qualifies_as": "eliminated"
        }
      ]
    },
    {
      "name": "H",
      "standings": [
        {
          "team": "Spain",
          "rating": 2021,
          "predicted_points": 9,
          "position": 1,
          "qualifies_as": "winner"
        },
        {
          "team": "Uruguay",
          "rating": 1836,
          "predicted_points": 6,
          "position": 2,
          "qualifies_as": "runner_up"
        },
        {
          "team": "Cape Verde",
          "rating": 1675,
          "predicted_points": 3,
          "position": 3,
          "qualifies_as": "eliminated"
        },
        {
          "team": "Saudi Arabia",
          "rating": 1639,
          "predicted_points": 0,
          "position": 4,
          "qualifies_as": "eliminated"
        }
      ]
    },
    {
      "name": "I",
      "standings": [
        {
          "team": "France",
          "rating": 1985,
          "predicted_points": 9,
          "position": 1,
          "qualifies_as": "winner"
        },
        {
          "team": "Senegal",
          "rating": 1899,
          "predicted_points": 6,
          "position": 2,
          "qualifies_as": "runner_up"
        },
        {
          "team": "Norway",
          "rating": 1881,
          "predicted_points": 3,
          "position": 3,
          "qualifies_as": "best_third"
        },
        {
          "team": "Iraq",
          "rating": 1675,
          "predicted_points": 0,
          "position": 4,
          "qualifies_as": "eliminated"
        }
      ]
    },
    {
      "name": "J",
      "standings": [
        {
          "team": "Argentina",
          "rating": 1952,
          "predicted_points": 9,
          "position": 1,
          "qualifies_as": "winner"
        },
        {
          "team": "Algeria",
          "rating": 1805,
          "predicted_points": 6,
          "position": 2,
          "qualifies_as": "runner_up"
        },
        {
          "team": "Austria",
          "rating": 1766,
          "predicted_points": 3,
          "position": 3,
          "qualifies_as": "best_third"
        },
        {
          "team": "Jordan",
          "rating": 1689,
          "predicted_points": 0,
          "position": 4,
          "qualifies_as": "eliminated"
        }
      ]
    },
    {
      "name": "K",
      "standings": [
        {
          "team": "Portugal",
          "rating": 1945,
          "predicted_points": 9,
          "position": 1,
          "qualifies_as": "winner"
        },
        {
          "team": "Colombia",
          "rating": 1924,
          "predicted_points": 6,
          "position": 2,
          "qualifies_as": "runner_up"
        },
        {
          "team": "DR Congo",
          "rating": 1766,
          "predicted_points": 3,
          "position": 3,
          "qualifies_as": "best_third"
        },
        {
          "team": "Uzbekistan",
          "rating": 1750,
          "predicted_points": 0,
          "position": 4,
          "qualifies_as": "eliminated"
        }
      ]
    },
    {
      "name": "L",
      "standings": [
        {
          "team": "England",
          "rating": 1895,
          "predicted_points": 9,
          "position": 1,
          "qualifies_as": "winner"
        },
        {
          "team": "Croatia",
          "rating": 1838,
          "predicted_points": 6,
          "position": 2,
          "qualifies_as": "runner_up"
        },
        {
          "team": "Panama",
          "rating": 1734,
          "predicted_points": 3,
          "position": 3,
          "qualifies_as": "eliminated"
        },
        {
          "team": "Ghana",
          "rating": 1703,
          "predicted_points": 0,
          "position": 4,
          "qualifies_as": "eliminated"
        }
      ]
    }
  ],
  "knockout": {
    "round_of_32": [
      {
        "team_a": "South Korea",
        "team_b": "Canada",
        "rating_a": 1774,
        "rating_b": 1797,
        "winner": "Canada"
      },
      {
        "team_a": "Ecuador",
        "team_b": "United States",
        "rating_a": 1906,
        "rating_b": 1771,
        "winner": "Ecuador"
      },
      {
        "team_a": "Japan",
        "team_b": "Morocco",
        "rating_a": 1903,
        "rating_b": 1864,
        "winner": "Japan"
      },
      {
        "team_a": "Brazil",
        "team_b": "Netherlands",
        "rating_a": 1937,
        "rating_b": 1891,
        "winner": "Brazil"
      },
      {
        "team_a": "France",
        "team_b": "Sweden",
        "rating_a": 1985,
        "rating_b": 1741,
        "winner": "France"
      },
      {
        "team_a": "Germany",
        "team_b": "Senegal",
        "rating_a": 1877,
        "rating_b": 1899,
        "winner": "Senegal"
      },
      {
        "team_a": "Mexico",
        "team_b": "Norway",
        "rating_a": 1792,
        "rating_b": 1881,
        "winner": "Norway"
      },
      {
        "team_a": "England",
        "team_b": "Ivory Coast",
        "rating_a": 1895,
        "rating_b": 1825,
        "winner": "England"
      },
      {
        "team_a": "Turkey",
        "team_b": "Austria",
        "rating_a": 1878,
        "rating_b": 1766,
        "winner": "Turkey"
      },
      {
        "team_a": "Belgium",
        "team_b": "DR Congo",
        "rating_a": 1870,
        "rating_b": 1766,
        "winner": "Belgium"
      },
      {
        "team_a": "Colombia",
        "team_b": "Croatia",
        "rating_a": 1924,
        "rating_b": 1838,
        "winner": "Colombia"
      },
      {
        "team_a": "Spain",
        "team_b": "Algeria",
        "rating_a": 2021,
        "rating_b": 1805,
        "winner": "Spain"
      },
      {
        "team_a": "Switzerland",
        "team_b": "Egypt",
        "rating_a": 1882,
        "rating_b": 1738,
        "winner": "Switzerland"
      },
      {
        "team_a": "Argentina",
        "team_b": "Uruguay",
        "rating_a": 1952,
        "rating_b": 1836,
        "winner": "Argentina"
      },
      {
        "team_a": "Portugal",
        "team_b": "Scotland",
        "rating_a": 1945,
        "rating_b": 1734,
        "winner": "Portugal"
      },
      {
        "team_a": "Paraguay",
        "team_b": "Iran",
        "rating_a": 1829,
        "rating_b": 1738,
        "winner": "Paraguay"
      }
    ],
    "round_of_16": [
      {
        "team_a": "Ecuador",
        "team_b": "France",
        "rating_a": 1906,
        "rating_b": 1985,
        "winner": "France"
      },
      {
        "team_a": "Canada",
        "team_b": "Japan",
        "rating_a": 1797,
        "rating_b": 1903,
        "winner": "Japan"
      },
      {
        "team_a": "Brazil",
        "team_b": "Senegal",
        "rating_a": 1937,
        "rating_b": 1899,
        "winner": "Brazil"
      },
      {
        "team_a": "Norway",
        "team_b": "England",
        "rating_a": 1881,
        "rating_b": 1895,
        "winner": "England"
      },
      {
        "team_a": "Colombia",
        "team_b": "Spain",
        "rating_a": 1924,
        "rating_b": 2021,
        "winner": "Spain"
      },
      {
        "team_a": "Turkey",
        "team_b": "Belgium",
        "rating_a": 1878,
        "rating_b": 1870,
        "winner": "Turkey"
      },
      {
        "team_a": "Argentina",
        "team_b": "Paraguay",
        "rating_a": 1952,
        "rating_b": 1829,
        "winner": "Argentina"
      },
      {
        "team_a": "Switzerland",
        "team_b": "Portugal",
        "rating_a": 1882,
        "rating_b": 1945,
        "winner": "Portugal"
      }
    ],
    "quarter_finals": [
      {
        "team_a": "France",
        "team_b": "Japan",
        "rating_a": 1985,
        "rating_b": 1903,
        "winner": "France"
      },
      {
        "team_a": "Spain",
        "team_b": "Turkey",
        "rating_a": 2021,
        "rating_b": 1878,
        "winner": "Spain"
      },
      {
        "team_a": "Brazil",
        "team_b": "England",
        "rating_a": 1937,
        "rating_b": 1895,
        "winner": "Brazil"
      },
      {
        "team_a": "Argentina",
        "team_b": "Portugal",
        "rating_a": 1952,
        "rating_b": 1945,
        "winner": "Argentina"
      }
    ],
    "semi_finals": [
      {
        "team_a": "France",
        "team_b": "Spain",
        "rating_a": 1985,
        "rating_b": 2021,
        "winner": "Spain"
      },
      {
        "team_a": "Brazil",
        "team_b": "Argentina",
        "rating_a": 1937,
        "rating_b": 1952,
        "winner": "Argentina"
      }
    ],
    "final": [
      {
        "team_a": "Spain",
        "team_b": "Argentina",
        "rating_a": 2021,
        "rating_b": 1952,
        "winner": "Spain"
      }
    ],
    "champion": "Spain"
  }
}